securepipe/__init__.py
securepipe/core.py
securepipe/utils.py
securepipe-0.1.0.dist-info/licenses/LICENSE
securepipe-0.1.0.dist-info/METADATA
securepipe-0.1.0.dist-info/WHEEL
securepipe-0.1.0.dist-info/top_level.txt
securepipe-0.1.0.dist-info/RECORD
