Metadata-Version: 2.4
Name: securepipe
Version: 0.1.0
Summary: A lightweight encryption library using HS256 with additional custom security layers. eg UUID and 2 layers of encryption
Author-email: Joseph Wathome <wathomejosephgathithi@gmail.com>
License: MIT
Project-URL: Homepage, https://github.com/Josewathome/securepipe
Project-URL: Issues, https://github.com/Josewathome/securepipe/issues
Classifier: Programming Language :: Python :: 3
Classifier: Programming Language :: Python :: 3.8
Classifier: License :: OSI Approved :: MIT License
Classifier: Operating System :: OS Independent
Classifier: Development Status :: 3 - Alpha
Classifier: Intended Audience :: Developers
Classifier: Topic :: Security :: Cryptography
Requires-Python: >=3.8
License-File: LICENSE
Requires-Dist: cryptography>=41.0.0
Requires-Dist: PyJWT>=2.8.0
Provides-Extra: dev
Requires-Dist: pytest>=8.0.0; extra == "dev"
Requires-Dist: pluggy>=1.6.0; extra == "dev"
Requires-Dist: tomli>=2.3.0; extra == "dev"
Requires-Dist: iniconfig>=2.1.0; extra == "dev"
Requires-Dist: Pygments>=2.19.0; extra == "dev"
Dynamic: license-file
